conPOV/__init__.py
conPOV/main.py
conPov-0.0.2.dist-info/LICENSE
conPov-0.0.2.dist-info/METADATA
conPov-0.0.2.dist-info/WHEEL
conPov-0.0.2.dist-info/top_level.txt
conPov-0.0.2.dist-info/RECORD
