Metadata-Version: 2.1
Name: conPov
Version: 0.0.2
Summary: Convolute a series over an integer number
Home-page: https://github.com/arjunjanamatti/CONPOV
Author: Aditya Pahuja
Author-email: adtiayphj19@gmail.com
Classifier: Programming Language :: Python :: 3
Classifier: License :: OSI Approved :: MIT License
Classifier: Operating System :: OS Independent
Requires-Python: >=3.7
License-File: LICENSE
